{
  "price": [
    {
      "name": "코스피지수",
      "link": "https://kr.investing.com/indices/kospi",
      "flagUrl": "https://flagcdn.com/16x12/kr.png",
      "values": [
        "3,953.76",
        "4,037.61",
        "3,887.32",
        "-72.69",
        "-1.81%"
      ],
      "time": "15:29:59",
      "marketStatus": "closed"
    },
    {
      "name": "코스피 50",
      "link": "https://kr.investing.com/indices/kospi-50",
      "flagUrl": "https://flagcdn.com/16x12/kr.png",
      "values": [
        "3,955.46",
        "4,046.59",
        "3,885.25",
        "-65.24",
        "-1.62%"
      ],
      "time": "15:29:59",
      "marketStatus": "closed"
    },
    {
      "name": "코스닥",
      "link": "https://kr.investing.com/indices/kosdaq",
      "flagUrl": "https://flagcdn.com/16x12/kr.png",
      "values": [
        "876.81",
        "894.83",
        "864.67",
        "-21.36",
        "-2.38%"
      ],
      "time": "15:29:59",
      "marketStatus": "closed"
    },
    {
      "name": "다우존스",
      "link": "https://kr.investing.com/indices/us-30",
      "flagUrl": "https://flagcdn.com/16x12/us.png",
      "values": [
        "46,912.30",
        "47,359.29",
        "46,787.44",
        "-398.70",
        "-0.84%"
      ],
      "time": "05:59:59",
      "marketStatus": "closed"
    },
    {
      "name": "S&P 500",
      "link": "https://kr.investing.com/indices/us-spx-500",
      "flagUrl": "https://flagcdn.com/16x12/us.png",
      "values": [
        "6,720.32",
        "6,796.68",
        "6,707.51",
        "-75.97",
        "-1.12%"
      ],
      "time": "05:59:59",
      "marketStatus": "closed"
    },
    {
      "name": "나스닥종합지수",
      "link": "https://kr.investing.com/indices/nasdaq-composite",
      "flagUrl": "https://flagcdn.com/16x12/us.png",
      "values": [
        "23,053.99",
        "23,469.55",
        "23,011.06",
        "-445.80",
        "-1.90%"
      ],
      "time": "05:59:59",
      "marketStatus": "closed"
    },
    {
      "name": "러셀 2000",
      "link": "https://kr.investing.com/indices/smallcap-2000",
      "flagUrl": "https://flagcdn.com/16x12/us.png",
      "values": [
        "2,418.82",
        "2,461.47",
        "2,417.09",
        "-45.96",
        "-1.86%"
      ],
      "time": "05:59:59",
      "marketStatus": "closed"
    },
    {
      "name": "CBOE VIX",
      "link": "https://kr.investing.com/indices/volatility-s-p-500",
      "flagUrl": "https://flagcdn.com/16x12/us.png",
      "values": [
        "19.69",
        "19.84",
        "19.50",
        "+0.19",
        "+0.97%"
      ],
      "time": "17:47:31",
      "marketStatus": "open"
    },
    {
      "name": "캐나다 S&P/TSX",
      "link": "https://kr.investing.com/indices/s-p-tsx-composite",
      "flagUrl": "https://flagcdn.com/16x12/ca.png",
      "values": [
        "29,868.59",
        "30,117.66",
        "29,815.10",
        "-234.89",
        "-0.78%"
      ],
      "time": "06:01:29",
      "marketStatus": "closed"
    },
    {
      "name": "브라질 보베스파",
      "link": "https://kr.investing.com/indices/bovespa",
      "flagUrl": "https://flagcdn.com/16x12/br.png",
      "values": [
        "153,339",
        "154,352",
        "153,235",
        "+44",
        "+0.03%"
      ],
      "time": "05:54:59",
      "marketStatus": "closed"
    },
    {
      "name": "S&P/BMV IPC",
      "link": "https://kr.investing.com/indices/ipc",
      "flagUrl": "https://flagcdn.com/16x12/mx.png",
      "values": [
        "63,093.12",
        "63,599.56",
        "62,996.49",
        "-285.39",
        "-0.45%"
      ],
      "time": "05:59:59",
      "marketStatus": "closed"
    },
    {
      "name": "DAX",
      "link": "https://kr.investing.com/indices/germany-30",
      "flagUrl": "https://flagcdn.com/16x12/de.png",
      "values": [
        "23,755.20",
        "23,840.28",
        "23,729.64",
        "+10.96",
        "+0.05%"
      ],
      "time": "17:46:51",
      "marketStatus": "open"
    },
    {
      "name": "영국 FTSE",
      "link": "https://kr.investing.com/indices/uk-100",
      "flagUrl": "https://flagcdn.com/16x12/gb.png",
      "values": [
        "9,711.65",
        "9,728.27",
        "9,706.45",
        "-24.13",
        "-0.25%"
      ],
      "time": "17:47:50",
      "marketStatus": "open"
    },
    {
      "name": "프랑스 CAC",
      "link": "https://kr.investing.com/indices/france-40",
      "flagUrl": "https://flagcdn.com/16x12/fr.png",
      "values": [
        "7,980.01",
        "8,000.99",
        "7,962.56",
        "+15.24",
        "+0.19%"
      ],
      "time": "17:47:45",
      "marketStatus": "open"
    },
    {
      "name": "유로 스톡스 50",
      "link": "https://kr.investing.com/indices/eu-stoxx50",
      "flagUrl": "https://flagcdn.com/16x12/eu.png",
      "values": [
        "5,618.15",
        "5,634.40",
        "5,608.55",
        "+6.97",
        "+0.12%"
      ],
      "time": "17:47:34",
      "marketStatus": "open"
    },
    {
      "name": "네덜란드 AEX",
      "link": "https://kr.investing.com/indices/netherlands-25",
      "flagUrl": "https://flagcdn.com/16x12/nl.png",
      "values": [
        "960.03",
        "963.81",
        "959.90",
        "-1.03",
        "-0.11%"
      ],
      "time": "17:46:30",
      "marketStatus": "open"
    },
    {
      "name": "스페인 IBEX",
      "link": "https://kr.investing.com/indices/spain-35",
      "flagUrl": "https://flagcdn.com/16x12/es.png",
      "values": [
        "16,044.50",
        "16,179.50",
        "16,037.49",
        "-75.60",
        "-0.47%"
      ],
      "time": "17:47:47",
      "marketStatus": "open"
    },
    {
      "name": "이탈리아 FTSE MIB",
      "link": "https://kr.investing.com/indices/it-mib-40",
      "flagUrl": "https://flagcdn.com/16x12/it.png",
      "values": [
        "43,227.00",
        "43,339.00",
        "43,130.00",
        "+158.31",
        "+0.37%"
      ],
      "time": "17:47:50",
      "marketStatus": "open"
    },
    {
      "name": "스위스 SMI",
      "link": "https://kr.investing.com/indices/switzerland-20",
      "flagUrl": "https://flagcdn.com/16x12/ch.png",
      "values": [
        "12,306.31",
        "12,333.31",
        "12,285.31",
        "+12.53",
        "+0.10%"
      ],
      "time": "17:47:47",
      "marketStatus": "open"
    },
    {
      "name": "PSI",
      "link": "https://kr.investing.com/indices/psi-20",
      "flagUrl": "https://flagcdn.com/16x12/pt.png",
      "values": [
        "8,293.09",
        "8,335.03",
        "8,288.87",
        "-83.62",
        "-1.00%"
      ],
      "time": "17:46:30",
      "marketStatus": "open"
    },
    {
      "name": "벨기에 BEL",
      "link": "https://kr.investing.com/indices/bel-20",
      "flagUrl": "https://flagcdn.com/16x12/be.png",
      "values": [
        "4,931.30",
        "4,951.00",
        "4,931.30",
        "+4.80",
        "+0.10%"
      ],
      "time": "17:46:45",
      "marketStatus": "open"
    },
    {
      "name": "ATX",
      "link": "https://kr.investing.com/indices/atx",
      "flagUrl": "https://flagcdn.com/16x12/at.png",
      "values": [
        "4,809.44",
        "4,813.07",
        "4,809.44",
        "-0.81",
        "-0.02%"
      ],
      "time": "17:15:00",
      "marketStatus": "open"
    },
    {
      "name": "스웨덴 OMXS",
      "link": "https://kr.investing.com/indices/omx-stockholm-30",
      "flagUrl": "https://flagcdn.com/16x12/se.png",
      "values": [
        "2,743.40",
        "2,756.65",
        "2,742.36",
        "-0.90",
        "-0.03%"
      ],
      "time": "17:46:44",
      "marketStatus": "open"
    },
    {
      "name": "MOEX Russia Index",
      "link": "https://kr.investing.com/indices/mcx",
      "flagUrl": "https://flagcdn.com/16x12/ru.png",
      "values": [
        "2,563.91",
        "2,568.41",
        "2,544.48",
        "+21.21",
        "+0.83%"
      ],
      "time": "17:46:41",
      "marketStatus": "open"
    },
    {
      "name": "RTSI 지수",
      "link": "https://kr.investing.com/indices/rtsi",
      "flagUrl": "https://flagcdn.com/16x12/ru.png",
      "values": [
        "992.53",
        "994.28",
        "983.24",
        "+8.21",
        "+0.83%"
      ],
      "time": "17:46:41",
      "marketStatus": "open"
    },
    {
      "name": "폴란드 WIG 20",
      "link": "https://kr.investing.com/indices/wig-20",
      "flagUrl": "https://flagcdn.com/16x12/pl.png",
      "values": [
        "3,005.37",
        "3,018.84",
        "2,993.40",
        "-1.21",
        "-0.04%"
      ],
      "time": "17:46:30",
      "marketStatus": "open"
    },
    {
      "name": "헝가리 BUX",
      "link": "https://kr.investing.com/indices/hungary-stock-market",
      "flagUrl": "https://flagcdn.com/16x12/hu.png",
      "values": [
        "106,933.50",
        "107,581.87",
        "106,718.65",
        "0.00",
        "0.00%"
      ],
      "time": "01:15:59",
      "marketStatus": "open"
    },
    {
      "name": "터키 BIST",
      "link": "https://kr.investing.com/indices/ise-100",
      "flagUrl": "https://flagcdn.com/16x12/tr.png",
      "values": [
        "10,963.45",
        "11,092.91",
        "10,962.43",
        "-109.82",
        "-0.99%"
      ],
      "time": "17:31:35",
      "marketStatus": "open"
    },
    {
      "name": "TA 35",
      "link": "https://kr.investing.com/indices/ta25",
      "flagUrl": "https://flagcdn.com/16x12/il.png",
      "values": [
        "3,335.93",
        "3,379.43",
        "3,329.39",
        "-15.05",
        "-0.45%"
      ],
      "time": "00:29:59",
      "marketStatus": "closed"
    },
    {
      "name": "사우디아라비아 Tadawul",
      "link": "https://kr.investing.com/indices/tasi",
      "flagUrl": "https://flagcdn.com/16x12/sa.png",
      "values": [
        "11,302.35",
        "11,321.17",
        "11,257.08",
        "+45.61",
        "+0.41%"
      ],
      "time": "06/11",
      "marketStatus": "closed"
    },
    {
      "name": "닛케이",
      "link": "https://kr.investing.com/indices/japan-ni225",
      "flagUrl": "https://flagcdn.com/16x12/jp.png",
      "values": [
        "50,270.50",
        "50,428.00",
        "49,639.50",
        "-613.18",
        "-1.21%"
      ],
      "time": "15:30:29",
      "marketStatus": "closed"
    },
    {
      "name": "호주 S&P/ASX",
      "link": "https://kr.investing.com/indices/aus-200",
      "flagUrl": "https://flagcdn.com/16x12/au.png",
      "values": [
        "8,769.70",
        "8,835.40",
        "8,756.40",
        "-58.60",
        "-0.66%"
      ],
      "time": "14:04:59",
      "marketStatus": "closed"
    },
    {
      "name": "상해종합",
      "link": "https://kr.investing.com/indices/shanghai-composite",
      "flagUrl": "https://flagcdn.com/16x12/cn.png",
      "values": [
        "3,997.56",
        "4,012.01",
        "3,993.69",
        "-10.20",
        "-0.25%"
      ],
      "time": "15:59:59",
      "marketStatus": "closed"
    },
    {
      "name": "SZSE Component",
      "link": "https://kr.investing.com/indices/szse-component",
      "flagUrl": "https://flagcdn.com/16x12/cn.png",
      "values": [
        "13,404.06",
        "13,496.70",
        "13,322.61",
        "-48.36",
        "-0.36%"
      ],
      "time": "16:44:59",
      "marketStatus": "closed"
    },
    {
      "name": "China A50",
      "link": "https://kr.investing.com/indices/ftse-china-a50",
      "flagUrl": "https://flagcdn.com/16x12/cn.png",
      "values": [
        "15,422.88",
        "15,507.95",
        "15,393.34",
        "-82.70",
        "-0.53%"
      ],
      "time": "15:59:59",
      "marketStatus": "closed"
    },
    {
      "name": "DJ Shanghai",
      "link": "https://kr.investing.com/indices/dj-shanghai",
      "flagUrl": "https://flagcdn.com/16x12/cn.png",
      "values": [
        "551.52",
        "553.83",
        "550.02",
        "-1.23",
        "-0.22%"
      ],
      "time": "15:59:59",
      "marketStatus": "closed"
    },
    {
      "name": "항셍",
      "link": "https://kr.investing.com/indices/hang-sen-40",
      "flagUrl": "https://flagcdn.com/16x12/hk.png",
      "values": [
        "26,241.83",
        "26,356.00",
        "26,132.50",
        "-244.07",
        "-0.92%"
      ],
      "time": "16:59:59",
      "marketStatus": "closed"
    },
    {
      "name": "대만 가권",
      "link": "https://kr.investing.com/indices/taiwan-weighted",
      "flagUrl": "https://flagcdn.com/16x12/tw.png",
      "values": [
        "27,717.06",
        "27,799.09",
        "27,373.05",
        "-399.50",
        "-1.42%"
      ],
      "time": "05/11",
      "marketStatus": "closed"
    },
    {
      "name": "SET",
      "link": "https://kr.investing.com/indices/thailand-set",
      "flagUrl": "https://flagcdn.com/16x12/th.png",
      "values": [
        "1,308.75",
        "1,314.63",
        "1,306.11",
        "-4.56",
        "-0.35%"
      ],
      "time": "17:31:27",
      "marketStatus": "open"
    },
    {
      "name": "인도네시아 IDX",
      "link": "https://kr.investing.com/indices/idx-composite",
      "flagUrl": "https://flagcdn.com/16x12/id.png",
      "values": [
        "8,391.39",
        "8,394.02",
        "8,332.60",
        "+54.34",
        "+0.65%"
      ],
      "time": "16:59:59",
      "marketStatus": "closed"
    },
    {
      "name": "Nifty 50",
      "link": "https://kr.investing.com/indices/s-p-cnx-nifty",
      "flagUrl": "https://flagcdn.com/16x12/in.png",
      "values": [
        "25,482.65",
        "25,551.25",
        "25,318.45",
        "-27.05",
        "-0.11%"
      ],
      "time": "17:47:31",
      "marketStatus": "open"
    },
    {
      "name": "인도 센섹스",
      "link": "https://kr.investing.com/indices/sensex",
      "flagUrl": "https://flagcdn.com/16x12/in.png",
      "values": [
        "83,174.56",
        "83,390.11",
        "82,670.95",
        "-136.45",
        "-0.16%"
      ],
      "time": "17:31:32",
      "marketStatus": "open"
    },
    {
      "name": "VN 30",
      "link": "https://kr.investing.com/indices/vn-30",
      "flagUrl": "https://flagcdn.com/16x12/vn.png",
      "values": [
        "1,824.71",
        "1,874.16",
        "1,817.93",
        "-44.89",
        "-2.40%"
      ],
      "time": "16:45:10",
      "marketStatus": "closed"
    }
  ],
  "performance": [
    {
      "name": "코스피지수",
      "link": "https://kr.investing.com/indices/kospi",
      "flagUrl": "https://flagcdn.com/16x12/kr.png",
      "values": [
        "-1.81%",
        "-3.74%",
        "+11.40%",
        "+64.78%",
        "+54.37%",
        "+64.81%"
      ]
    },
    {
      "name": "코스피 50",
      "link": "https://kr.investing.com/indices/kospi-50",
      "flagUrl": "https://flagcdn.com/16x12/kr.png",
      "values": [
        "-1.62%",
        "-3.56%",
        "+14.85%",
        "+78.71%",
        "+68.10%",
        "+84.02%"
      ]
    },
    {
      "name": "코스닥",
      "link": "https://kr.investing.com/indices/kosdaq",
      "flagUrl": "https://flagcdn.com/16x12/kr.png",
      "values": [
        "-2.38%",
        "-2.62%",
        "+2.64%",
        "+29.29%",
        "+17.95%",
        "+22.92%"
      ]
    },
    {
      "name": "다우존스",
      "link": "https://kr.investing.com/indices/us-30",
      "flagUrl": "https://flagcdn.com/16x12/us.png",
      "values": [
        "-0.84%",
        "-1.37%",
        "+0.67%",
        "+10.27%",
        "+6.65%",
        "+41.47%"
      ]
    },
    {
      "name": "S&P 500",
      "link": "https://kr.investing.com/indices/us-spx-500",
      "flagUrl": "https://flagcdn.com/16x12/us.png",
      "values": [
        "-1.12%",
        "-1.75%",
        "-0.49%",
        "+14.26%",
        "+12.09%",
        "+75.55%"
      ]
    },
    {
      "name": "나스닥종합지수",
      "link": "https://kr.investing.com/indices/nasdaq-composite",
      "flagUrl": "https://flagcdn.com/16x12/us.png",
      "values": [
        "-1.90%",
        "-2.83%",
        "+0.05%",
        "+19.38%",
        "+19.53%",
        "+117.16%"
      ]
    },
    {
      "name": "러셀 2000",
      "link": "https://kr.investing.com/indices/smallcap-2000",
      "flagUrl": "https://flagcdn.com/16x12/us.png",
      "values": [
        "-1.86%",
        "-2.44%",
        "-2.62%",
        "+8.46%",
        "+0.80%",
        "+33.72%"
      ]
    },
    {
      "name": "CBOE VIX",
      "link": "https://kr.investing.com/indices/volatility-s-p-500",
      "flagUrl": "https://flagcdn.com/16x12/us.png",
      "values": [
        "+0.97%",
        "+13.19%",
        "+21.10%",
        "+13.78%",
        "+32.13%",
        "-22.71%"
      ]
    },
    {
      "name": "캐나다 S&P/TSX",
      "link": "https://kr.investing.com/indices/s-p-tsx-composite",
      "flagUrl": "https://flagcdn.com/16x12/ca.png",
      "values": [
        "-0.78%",
        "-1.30%",
        "-2.08%",
        "+20.79%",
        "+20.64%",
        "+51.92%"
      ]
    },
    {
      "name": "브라질 보베스파",
      "link": "https://kr.investing.com/indices/bovespa",
      "flagUrl": "https://flagcdn.com/16x12/br.png",
      "values": [
        "+0.03%",
        "+2.54%",
        "+7.87%",
        "+27.48%",
        "+19.96%",
        "+32.01%"
      ]
    },
    {
      "name": "S&P/BMV IPC",
      "link": "https://kr.investing.com/indices/ipc",
      "flagUrl": "https://flagcdn.com/16x12/mx.png",
      "values": [
        "-0.45%",
        "+0.52%",
        "+3.62%",
        "+27.43%",
        "+21.70%",
        "+23.98%"
      ]
    },
    {
      "name": "DAX",
      "link": "https://kr.investing.com/indices/germany-30",
      "flagUrl": "https://flagcdn.com/16x12/de.png",
      "values": [
        "+0.05%",
        "-0.88%",
        "-3.45%",
        "+19.28%",
        "+23.59%",
        "+73.49%"
      ]
    },
    {
      "name": "영국 FTSE",
      "link": "https://kr.investing.com/indices/uk-100",
      "flagUrl": "https://flagcdn.com/16x12/gb.png",
      "values": [
        "-0.25%",
        "-0.07%",
        "+1.69%",
        "+18.81%",
        "+20.29%",
        "+32.91%"
      ]
    },
    {
      "name": "프랑스 CAC",
      "link": "https://kr.investing.com/indices/france-40",
      "flagUrl": "https://flagcdn.com/16x12/fr.png",
      "values": [
        "+0.19%",
        "-1.85%",
        "-1.11%",
        "+8.00%",
        "+8.62%",
        "+23.74%"
      ]
    },
    {
      "name": "유로 스톡스 50",
      "link": "https://kr.investing.com/indices/eu-stoxx50",
      "flagUrl": "https://flagcdn.com/16x12/eu.png",
      "values": [
        "+0.12%",
        "-0.86%",
        "-0.65%",
        "+14.65%",
        "+16.88%",
        "+50.12%"
      ]
    },
    {
      "name": "네덜란드 AEX",
      "link": "https://kr.investing.com/indices/netherlands-25",
      "flagUrl": "https://flagcdn.com/16x12/nl.png",
      "values": [
        "-0.11%",
        "-1.14%",
        "-0.03%",
        "+9.30%",
        "+9.86%",
        "+40.41%"
      ]
    },
    {
      "name": "스페인 IBEX",
      "link": "https://kr.investing.com/indices/spain-35",
      "flagUrl": "https://flagcdn.com/16x12/es.png",
      "values": [
        "-0.47%",
        "+0.12%",
        "+2.39%",
        "+38.44%",
        "+38.96%",
        "+100.68%"
      ]
    },
    {
      "name": "이탈리아 FTSE MIB",
      "link": "https://kr.investing.com/indices/it-mib-40",
      "flagUrl": "https://flagcdn.com/16x12/it.png",
      "values": [
        "+0.37%",
        "-0.02%",
        "-0.73%",
        "+26.26%",
        "+27.64%",
        "+82.18%"
      ]
    },
    {
      "name": "스위스 SMI",
      "link": "https://kr.investing.com/indices/switzerland-20",
      "flagUrl": "https://flagcdn.com/16x12/ch.png",
      "values": [
        "+0.10%",
        "+0.56%",
        "-2.73%",
        "+6.05%",
        "+4.29%",
        "+13.64%"
      ]
    },
    {
      "name": "PSI",
      "link": "https://kr.investing.com/indices/psi-20",
      "flagUrl": "https://flagcdn.com/16x12/pt.png",
      "values": [
        "-1.00%",
        "-1.55%",
        "+1.81%",
        "+30.09%",
        "+29.88%",
        "+43.77%"
      ]
    },
    {
      "name": "벨기에 BEL",
      "link": "https://kr.investing.com/indices/bel-20",
      "flagUrl": "https://flagcdn.com/16x12/be.png",
      "values": [
        "+0.10%",
        "+0.69%",
        "-0.08%",
        "+15.75%",
        "+15.72%",
        "+35.96%"
      ]
    },
    {
      "name": "ATX",
      "link": "https://kr.investing.com/indices/atx",
      "flagUrl": "https://flagcdn.com/16x12/at.png",
      "values": [
        "-0.02%",
        "+0.03%",
        "+2.27%",
        "+31.30%",
        "+35.47%",
        "+52.26%"
      ]
    },
    {
      "name": "스웨덴 OMXS",
      "link": "https://kr.investing.com/indices/omx-stockholm-30",
      "flagUrl": "https://flagcdn.com/16x12/se.png",
      "values": [
        "-0.03%",
        "-0.79%",
        "+0.43%",
        "+10.55%",
        "+7.28%",
        "+34.83%"
      ]
    },
    {
      "name": "MOEX Russia Index",
      "link": "https://kr.investing.com/indices/mcx",
      "flagUrl": "https://flagcdn.com/16x12/ru.png",
      "values": [
        "+0.83%",
        "+1.46%",
        "-0.02%",
        "-11.14%",
        "-6.31%",
        "+16.07%"
      ]
    },
    {
      "name": "RTSI 지수",
      "link": "https://kr.investing.com/indices/rtsi",
      "flagUrl": "https://flagcdn.com/16x12/ru.png",
      "values": [
        "+0.83%",
        "+0.95%",
        "+0.19%",
        "+11.03%",
        "+12.63%",
        "-13.24%"
      ]
    },
    {
      "name": "폴란드 WIG 20",
      "link": "https://kr.investing.com/indices/wig-20",
      "flagUrl": "https://flagcdn.com/16x12/pl.png",
      "values": [
        "-0.04%",
        "+0.47%",
        "+4.28%",
        "+36.92%",
        "+30.59%",
        "+82.48%"
      ]
    },
    {
      "name": "헝가리 BUX",
      "link": "https://kr.investing.com/indices/hungary-stock-market",
      "flagUrl": "https://flagcdn.com/16x12/hu.png",
      "values": [
        "0.00%",
        "-0.36%",
        "+5.03%",
        "+34.80%",
        "+40.24%",
        "+143.91%"
      ]
    },
    {
      "name": "터키 BIST",
      "link": "https://kr.investing.com/indices/ise-100",
      "flagUrl": "https://flagcdn.com/16x12/tr.png",
      "values": [
        "-0.99%",
        "+0.31%",
        "+2.31%",
        "+11.95%",
        "+19.82%",
        "+152.40%"
      ]
    },
    {
      "name": "TA 35",
      "link": "https://kr.investing.com/indices/ta25",
      "flagUrl": "https://flagcdn.com/16x12/il.png",
      "values": [
        "-0.45%",
        "+1.91%",
        "+4.13%",
        "+39.29%",
        "+49.59%",
        "+72.19%"
      ]
    },
    {
      "name": "사우디아라비아 Tadawul",
      "link": "https://kr.investing.com/indices/tasi",
      "flagUrl": "https://flagcdn.com/16x12/sa.png",
      "values": [
        "+0.41%",
        "-3.03%",
        "-2.22%",
        "-6.10%",
        "-6.83%",
        "-1.60%"
      ]
    },
    {
      "name": "닛케이",
      "link": "https://kr.investing.com/indices/japan-ni225",
      "flagUrl": "https://flagcdn.com/16x12/jp.png",
      "values": [
        "-1.21%",
        "-4.08%",
        "+5.31%",
        "+26.01%",
        "+27.27%",
        "+80.36%"
      ]
    },
    {
      "name": "호주 S&P/ASX",
      "link": "https://kr.investing.com/indices/aus-200",
      "flagUrl": "https://flagcdn.com/16x12/au.png",
      "values": [
        "-0.66%",
        "-1.26%",
        "-1.99%",
        "+7.48%",
        "+5.72%",
        "+26.02%"
      ]
    },
    {
      "name": "상해종합",
      "link": "https://kr.investing.com/indices/shanghai-composite",
      "flagUrl": "https://flagcdn.com/16x12/cn.png",
      "values": [
        "-0.25%",
        "+1.08%",
        "+2.96%",
        "+19.27%",
        "+15.79%",
        "+30.45%"
      ]
    },
    {
      "name": "SZSE Component",
      "link": "https://kr.investing.com/indices/szse-component",
      "flagUrl": "https://flagcdn.com/16x12/cn.png",
      "values": [
        "-0.36%",
        "+0.19%",
        "-0.91%",
        "+28.70%",
        "+20.09%",
        "+20.29%"
      ]
    },
    {
      "name": "China A50",
      "link": "https://kr.investing.com/indices/ftse-china-a50",
      "flagUrl": "https://flagcdn.com/16x12/cn.png",
      "values": [
        "-0.53%",
        "+0.96%",
        "+1.85%",
        "+14.13%",
        "+11.53%",
        "+28.04%"
      ]
    },
    {
      "name": "DJ Shanghai",
      "link": "https://kr.investing.com/indices/dj-shanghai",
      "flagUrl": "https://flagcdn.com/16x12/cn.png",
      "values": [
        "-0.22%",
        "+0.80%",
        "+0.90%",
        "+19.70%",
        "+14.04%",
        "+25.04%"
      ]
    },
    {
      "name": "항셍",
      "link": "https://kr.investing.com/indices/hang-sen-40",
      "flagUrl": "https://flagcdn.com/16x12/hk.png",
      "values": [
        "-0.92%",
        "+1.29%",
        "-2.19%",
        "+30.82%",
        "+26.60%",
        "+58.49%"
      ]
    },
    {
      "name": "대만 가권",
      "link": "https://kr.investing.com/indices/taiwan-weighted",
      "flagUrl": "https://flagcdn.com/16x12/tw.png",
      "values": [
        "-1.42%",
        "-1.83%",
        "+2.41%",
        "+20.33%",
        "+17.68%",
        "+107.65%"
      ]
    },
    {
      "name": "SET",
      "link": "https://kr.investing.com/indices/thailand-set",
      "flagUrl": "https://flagcdn.com/16x12/th.png",
      "values": [
        "-0.35%",
        "-0.10%",
        "+0.25%",
        "-6.57%",
        "-10.69%",
        "-19.87%"
      ]
    },
    {
      "name": "인도네시아 IDX",
      "link": "https://kr.investing.com/indices/idx-composite",
      "flagUrl": "https://flagcdn.com/16x12/id.png",
      "values": [
        "+0.65%",
        "+2.73%",
        "+2.70%",
        "+18.45%",
        "+15.08%",
        "+18.95%"
      ]
    },
    {
      "name": "Nifty 50",
      "link": "https://kr.investing.com/indices/s-p-cnx-nifty",
      "flagUrl": "https://flagcdn.com/16x12/in.png",
      "values": [
        "-0.11%",
        "-0.94%",
        "+1.73%",
        "+7.76%",
        "+5.51%",
        "+39.98%"
      ]
    },
    {
      "name": "인도 센섹스",
      "link": "https://kr.investing.com/indices/sensex",
      "flagUrl": "https://flagcdn.com/16x12/in.png",
      "values": [
        "-0.16%",
        "-0.83%",
        "+1.79%",
        "+6.53%",
        "+4.72%",
        "+36.04%"
      ]
    },
    {
      "name": "VN 30",
      "link": "https://kr.investing.com/indices/vn-30",
      "flagUrl": "https://flagcdn.com/16x12/vn.png",
      "values": [
        "-2.40%",
        "-3.22%",
        "-5.11%",
        "+35.69%",
        "+38.51%",
        "+86.18%"
      ]
    }
  ],
  "technical": [
    {
      "name": "코스피지수",
      "link": "https://kr.investing.com/indices/kospi",
      "flagUrl": "https://flagcdn.com/16x12/kr.png",
      "values": [
        "적극 매도",
        "적극 매수",
        "적극 매수",
        "적극 매수"
      ]
    },
    {
      "name": "코스피 50",
      "link": "https://kr.investing.com/indices/kospi-50",
      "flagUrl": "https://flagcdn.com/16x12/kr.png",
      "values": [
        "적극 매도",
        "적극 매수",
        "적극 매수",
        "적극 매수"
      ]
    },
    {
      "name": "코스닥",
      "link": "https://kr.investing.com/indices/kosdaq",
      "flagUrl": "https://flagcdn.com/16x12/kr.png",
      "values": [
        "적극 매도",
        "중립",
        "적극 매수",
        "적극 매수"
      ]
    },
    {
      "name": "다우존스",
      "link": "https://kr.investing.com/indices/us-30",
      "flagUrl": "https://flagcdn.com/16x12/us.png",
      "values": [
        "적극 매도",
        "중립",
        "적극 매수",
        "적극 매수"
      ]
    },
    {
      "name": "S&P 500",
      "link": "https://kr.investing.com/indices/us-spx-500",
      "flagUrl": "https://flagcdn.com/16x12/us.png",
      "values": [
        "적극 매도",
        "중립",
        "적극 매수",
        "적극 매수"
      ]
    },
    {
      "name": "나스닥종합지수",
      "link": "https://kr.investing.com/indices/nasdaq-composite",
      "flagUrl": "https://flagcdn.com/16x12/us.png",
      "values": [
        "적극 매도",
        "중립",
        "적극 매수",
        "적극 매수"
      ]
    },
    {
      "name": "러셀 2000",
      "link": "https://kr.investing.com/indices/smallcap-2000",
      "flagUrl": "https://flagcdn.com/16x12/us.png",
      "values": [
        "적극 매도",
        "적극 매도",
        "적극 매수",
        "적극 매수"
      ]
    },
    {
      "name": "CBOE VIX",
      "link": "https://kr.investing.com/indices/volatility-s-p-500",
      "flagUrl": "https://flagcdn.com/16x12/us.png",
      "values": [
        "적극 매수",
        "적극 매수",
        "매수",
        "적극 매수"
      ]
    },
    {
      "name": "캐나다 S&P/TSX",
      "link": "https://kr.investing.com/indices/s-p-tsx-composite",
      "flagUrl": "https://flagcdn.com/16x12/ca.png",
      "values": [
        "적극 매도",
        "매도",
        "적극 매수",
        "적극 매수"
      ]
    },
    {
      "name": "브라질 보베스파",
      "link": "https://kr.investing.com/indices/bovespa",
      "flagUrl": "https://flagcdn.com/16x12/br.png",
      "values": [
        "적극 매수",
        "적극 매수",
        "적극 매수",
        "적극 매수"
      ]
    },
    {
      "name": "S&P/BMV IPC",
      "link": "https://kr.investing.com/indices/ipc",
      "flagUrl": "https://flagcdn.com/16x12/mx.png",
      "values": [
        "중립",
        "적극 매수",
        "적극 매수",
        "적극 매수"
      ]
    },
    {
      "name": "DAX",
      "link": "https://kr.investing.com/indices/germany-30",
      "flagUrl": "https://flagcdn.com/16x12/de.png",
      "values": [
        "적극 매도",
        "적극 매도",
        "중립",
        "적극 매수"
      ]
    },
    {
      "name": "영국 FTSE",
      "link": "https://kr.investing.com/indices/uk-100",
      "flagUrl": "https://flagcdn.com/16x12/gb.png",
      "values": [
        "적극 매도",
        "적극 매수",
        "적극 매수",
        "적극 매수"
      ]
    },
    {
      "name": "프랑스 CAC",
      "link": "https://kr.investing.com/indices/france-40",
      "flagUrl": "https://flagcdn.com/16x12/fr.png",
      "values": [
        "적극 매도",
        "적극 매도",
        "적극 매수",
        "적극 매수"
      ]
    },
    {
      "name": "유로 스톡스 50",
      "link": "https://kr.investing.com/indices/eu-stoxx50",
      "flagUrl": "https://flagcdn.com/16x12/eu.png",
      "values": [
        "적극 매도",
        "중립",
        "적극 매수",
        "적극 매수"
      ]
    },
    {
      "name": "네덜란드 AEX",
      "link": "https://kr.investing.com/indices/netherlands-25",
      "flagUrl": "https://flagcdn.com/16x12/nl.png",
      "values": [
        "적극 매도",
        "매도",
        "적극 매수",
        "적극 매수"
      ]
    },
    {
      "name": "스페인 IBEX",
      "link": "https://kr.investing.com/indices/spain-35",
      "flagUrl": "https://flagcdn.com/16x12/es.png",
      "values": [
        "중립",
        "적극 매수",
        "적극 매수",
        "적극 매수"
      ]
    },
    {
      "name": "이탈리아 FTSE MIB",
      "link": "https://kr.investing.com/indices/it-mib-40",
      "flagUrl": "https://flagcdn.com/16x12/it.png",
      "values": [
        "중립",
        "적극 매수",
        "적극 매수",
        "적극 매수"
      ]
    },
    {
      "name": "스위스 SMI",
      "link": "https://kr.investing.com/indices/switzerland-20",
      "flagUrl": "https://flagcdn.com/16x12/ch.png",
      "values": [
        "적극 매도",
        "적극 매도",
        "매수",
        "적극 매수"
      ]
    },
    {
      "name": "PSI",
      "link": "https://kr.investing.com/indices/psi-20",
      "flagUrl": "https://flagcdn.com/16x12/pt.png",
      "values": [
        "적극 매도",
        "중립",
        "적극 매수",
        "적극 매수"
      ]
    },
    {
      "name": "벨기에 BEL",
      "link": "https://kr.investing.com/indices/bel-20",
      "flagUrl": "https://flagcdn.com/16x12/be.png",
      "values": [
        "적극 매수",
        "중립",
        "적극 매수",
        "적극 매수"
      ]
    },
    {
      "name": "ATX",
      "link": "https://kr.investing.com/indices/atx",
      "flagUrl": "https://flagcdn.com/16x12/at.png",
      "values": [
        "적극 매수",
        "적극 매수",
        "적극 매수",
        "적극 매수"
      ]
    },
    {
      "name": "스웨덴 OMXS",
      "link": "https://kr.investing.com/indices/omx-stockholm-30",
      "flagUrl": "https://flagcdn.com/16x12/se.png",
      "values": [
        "적극 매도",
        "중립",
        "적극 매수",
        "적극 매수"
      ]
    },
    {
      "name": "MOEX Russia Index",
      "link": "https://kr.investing.com/indices/mcx",
      "flagUrl": "https://flagcdn.com/16x12/ru.png",
      "values": [
        "적극 매수",
        "매도",
        "적극 매도",
        "적극 매도"
      ]
    },
    {
      "name": "RTSI 지수",
      "link": "https://kr.investing.com/indices/rtsi",
      "flagUrl": "https://flagcdn.com/16x12/ru.png",
      "values": [
        "중립",
        "적극 매도",
        "적극 매도",
        "적극 매도"
      ]
    },
    {
      "name": "폴란드 WIG 20",
      "link": "https://kr.investing.com/indices/wig-20",
      "flagUrl": "https://flagcdn.com/16x12/pl.png",
      "values": [
        "매수",
        "적극 매수",
        "적극 매수",
        "적극 매수"
      ]
    },
    {
      "name": "헝가리 BUX",
      "link": "https://kr.investing.com/indices/hungary-stock-market",
      "flagUrl": "https://flagcdn.com/16x12/hu.png",
      "values": [
        "",
        "적극 매수",
        "적극 매수",
        "적극 매수"
      ]
    },
    {
      "name": "터키 BIST",
      "link": "https://kr.investing.com/indices/ise-100",
      "flagUrl": "https://flagcdn.com/16x12/tr.png",
      "values": [
        "중립",
        "적극 매수",
        "적극 매수",
        "적극 매수"
      ]
    },
    {
      "name": "TA 35",
      "link": "https://kr.investing.com/indices/ta25",
      "flagUrl": "https://flagcdn.com/16x12/il.png",
      "values": [
        "중립",
        "적극 매수",
        "적극 매수",
        "적극 매수"
      ]
    },
    {
      "name": "사우디아라비아 Tadawul",
      "link": "https://kr.investing.com/indices/tasi",
      "flagUrl": "https://flagcdn.com/16x12/sa.png",
      "values": [
        "적극 매도",
        "적극 매도",
        "중립",
        "중립"
      ]
    },
    {
      "name": "닛케이",
      "link": "https://kr.investing.com/indices/japan-ni225",
      "flagUrl": "https://flagcdn.com/16x12/jp.png",
      "values": [
        "중립",
        "매수",
        "적극 매수",
        "적극 매수"
      ]
    },
    {
      "name": "호주 S&P/ASX",
      "link": "https://kr.investing.com/indices/aus-200",
      "flagUrl": "https://flagcdn.com/16x12/au.png",
      "values": [
        "적극 매도",
        "적극 매도",
        "중립",
        "적극 매수"
      ]
    },
    {
      "name": "상해종합",
      "link": "https://kr.investing.com/indices/shanghai-composite",
      "flagUrl": "https://flagcdn.com/16x12/cn.png",
      "values": [
        "적극 매수",
        "적극 매수",
        "적극 매수",
        "적극 매수"
      ]
    },
    {
      "name": "SZSE Component",
      "link": "https://kr.investing.com/indices/szse-component",
      "flagUrl": "https://flagcdn.com/16x12/cn.png",
      "values": [
        "매수",
        "적극 매수",
        "적극 매수",
        "적극 매수"
      ]
    },
    {
      "name": "China A50",
      "link": "https://kr.investing.com/indices/ftse-china-a50",
      "flagUrl": "https://flagcdn.com/16x12/cn.png",
      "values": [
        "매수",
        "적극 매수",
        "적극 매수",
        "적극 매수"
      ]
    },
    {
      "name": "DJ Shanghai",
      "link": "https://kr.investing.com/indices/dj-shanghai",
      "flagUrl": "https://flagcdn.com/16x12/cn.png",
      "values": [
        "적극 매수",
        "적극 매수",
        "적극 매수",
        "적극 매수"
      ]
    },
    {
      "name": "항셍",
      "link": "https://kr.investing.com/indices/hang-sen-40",
      "flagUrl": "https://flagcdn.com/16x12/hk.png",
      "values": [
        "중립",
        "매수",
        "적극 매수",
        "적극 매수"
      ]
    },
    {
      "name": "대만 가권",
      "link": "https://kr.investing.com/indices/taiwan-weighted",
      "flagUrl": "https://flagcdn.com/16x12/tw.png",
      "values": [
        "",
        "중립",
        "적극 매수",
        "적극 매수"
      ]
    },
    {
      "name": "SET",
      "link": "https://kr.investing.com/indices/thailand-set",
      "flagUrl": "https://flagcdn.com/16x12/th.png",
      "values": [
        "중립",
        "중립",
        "적극 매수",
        "중립"
      ]
    },
    {
      "name": "인도네시아 IDX",
      "link": "https://kr.investing.com/indices/idx-composite",
      "flagUrl": "https://flagcdn.com/16x12/id.png",
      "values": [
        "적극 매수",
        "적극 매수",
        "적극 매수",
        "적극 매수"
      ]
    },
    {
      "name": "Nifty 50",
      "link": "https://kr.investing.com/indices/s-p-cnx-nifty",
      "flagUrl": "https://flagcdn.com/16x12/in.png",
      "values": [
        "매도",
        "매도",
        "적극 매수",
        "적극 매수"
      ]
    },
    {
      "name": "인도 센섹스",
      "link": "https://kr.investing.com/indices/sensex",
      "flagUrl": "https://flagcdn.com/16x12/in.png",
      "values": [
        "중립",
        "매도",
        "적극 매수",
        "적극 매수"
      ]
    },
    {
      "name": "VN 30",
      "link": "https://kr.investing.com/indices/vn-30",
      "flagUrl": "https://flagcdn.com/16x12/vn.png",
      "values": [
        "적극 매도",
        "적극 매도",
        "적극 매수",
        "적극 매수"
      ]
    }
  ],
  "lastUpdate": "2025-11-07T08:52:17.748Z"
}